MANIFEST.in
setup.py
./loq2/native/block/api.cpp
./loq2/native/block/iblock.cpp
./loq2/native/block/lblock.cpp
./loq2/native/map/map.cpp
./loq2/native/point/api.cpp
./loq2/native/point/point.cpp
./loq2/native/state/api.cpp
./loq2/native/state/cross.cpp
./loq2/native/state/endable.cpp
./loq2/native/state/mask.cpp
./loq2/native/state/move.cpp
./loq2/native/state/place.cpp
./loq2/native/state/util.cpp
loq2/__init__.py
loq2/game.py
loq2/lib.py
loq2/run.py
loq2/str.py
loq2.egg-info/PKG-INFO
loq2.egg-info/SOURCES.txt
loq2.egg-info/dependency_links.txt
loq2.egg-info/top_level.txt
loq2/native/library.h
loq2/native/type.h
loq2/native/util.h
loq2/native/block/block.h
loq2/native/map/map.h
loq2/native/point/point.h
loq2/native/state/state.h
loq2/types/block.py
loq2/types/map.py
loq2/types/point.py
loq2/types/state.py