Metadata-Version: 2.1
Name: loq2
Version: 0.3.7
Summary: League of Quoridor
Home-page: https://github.com/seo-rii/loq2
Author: seorii
Author-email: me@seorii.page
Classifier: Programming Language :: Python :: 3
Classifier: License :: OSI Approved :: MIT License
Classifier: Operating System :: OS Independent
Requires-Python: >=3.6
